sqlalchemy_seed/__init__.py
sqlalchemy_seed/mixin.py
sqlalchemy_seed-0.3.0.dist-info/DESCRIPTION.rst
sqlalchemy_seed-0.3.0.dist-info/METADATA
sqlalchemy_seed-0.3.0.dist-info/RECORD
sqlalchemy_seed-0.3.0.dist-info/WHEEL
sqlalchemy_seed-0.3.0.dist-info/metadata.json
sqlalchemy_seed-0.3.0.dist-info/top_level.txt
