Metadata-Version: 2.0
Name: sqlalchemy-seed
Version: 0.3.0
Summary: sqlalchemy_seed is simple data seeder using SQLAlchmy.
Home-page: http://github.com/heavenshell/py-sqlalchemy_seed
Author: Shinya Ohyanagi
Author-email: sohyanagi@gmail.com
License: BSD
Platform: any
Classifier: Development Status :: 4 - Beta
Classifier: Topic :: Database
Classifier: Intended Audience :: Developers
Classifier: License :: OSI Approved :: BSD License
Classifier: Operating System :: OS Independent
Classifier: Programming Language :: Python
Requires-Dist: sqlalchemy
Requires-Dist: pyyaml
Requires-Dist: flake8
